MANIFEST.in
setup.py
sqldeveloperpassworddecryptor/README.md
sqldeveloperpassworddecryptor/__init__.py
sqldeveloperpassworddecryptor/sqldeveloperpassworddecryptor.jy
sqldeveloperpassworddecryptor/sqldeveloperpassworddecryptor.py
sqldeveloperpassworddecryptor.egg-info/PKG-INFO
sqldeveloperpassworddecryptor.egg-info/SOURCES.txt
sqldeveloperpassworddecryptor.egg-info/dependency_links.txt
sqldeveloperpassworddecryptor.egg-info/entry_points.txt
sqldeveloperpassworddecryptor.egg-info/requires.txt
sqldeveloperpassworddecryptor.egg-info/top_level.txt