Metadata-Version: 2.1
Name: sqldeveloperpassworddecryptor
Version: 1.3
Summary: A simple script to decrypt stored passwords from the Oracle SQL Developer IDE
Home-page: https://github.com/maaaaz/sqldeveloperpassworddecryptor
Author: Thomas D.
Author-email: tdebize@mail.com
License: LGPL
Keywords: oracle sqldeveloper password decryptor
Platform: UNKNOWN
Classifier: Topic :: Security
Classifier: Development Status :: 5 - Production/Stable
Classifier: Intended Audience :: Information Technology
Classifier: Programming Language :: Python :: 3
Classifier: Programming Language :: Python :: 2.7
Classifier: License :: OSI Approved :: GNU Library or Lesser General Public License (LGPL)
Requires-Python: >=2.7
